rabbitplus.py
rabbitplus-0.0.1.dist-info/METADATA
rabbitplus-0.0.1.dist-info/WHEEL
rabbitplus-0.0.1.dist-info/entry_points.txt
rabbitplus-0.0.1.dist-info/top_level.txt
rabbitplus-0.0.1.dist-info/RECORD
