Metadata-Version: 2.1
Name: rabbitplus
Version: 0.0.1
Summary: Rabbit MQ消息工具（生产者、消费者封装）。
Home-page: https://github.com/kancyframework/python-plugins/tree/main/rabbitplus
Author: kancy
Author-email: 793272861@qq.com
License: MIT
Platform: UNKNOWN
Classifier: License :: OSI Approved :: MIT License
Classifier: Programming Language :: Python
Classifier: Programming Language :: Python :: 3
Classifier: Programming Language :: Python :: 3.6
Classifier: Programming Language :: Python :: Implementation :: CPython
Classifier: Programming Language :: Python :: Implementation :: PyPy
Requires-Python: >=3
Requires-Dist: pika
Provides-Extra: threading_feature
Requires-Dist: threading ; extra == 'threading_feature'
